retirepy/__about__.py
retirepy/__init__.py
retirepy/cash_flow.py
retirepy/future_value.py
retirepy/models.py
retirepy-0.0.1.dist-info/METADATA
retirepy-0.0.1.dist-info/WHEEL
retirepy-0.0.1.dist-info/licenses/LICENSE
retirepy-0.0.1.dist-info/RECORD
